retrofit/MachineLearning.py
retrofit/__init__.py
retrofit/reporting.py
retrofit/utils.py
retrofit/images/Categorical_PDP.PNG
retrofit/images/Confusion_Matrix.PNG
retrofit/images/Documentation.PNG
retrofit/images/FeatureEngineeringAll.PNG
retrofit/images/Numeric_PDP.PNG
retrofit/images/PR_Plot.PNG
retrofit/images/PackageLogo.PNG
retrofit/images/Predicted_Distribution_Plot.PNG
retrofit/images/ROC_Plot.PNG
retrofit/images/Regression_Calibration_Plot.PNG
retrofit/images/Regression_Light.PNG
retrofit/images/Regression_Neon.PNG
retrofit/images/Regression_Scatter_Plot.PNG
retrofit/images/Residual_Distribution_Plot.PNG
retrofit/images/Residuals_vs_Predicted_Plot.PNG
retrofit/images/RetroFitLogo.png
retrofit/images/Shap_PDP.PNG
retrofit/images/Shap_Summary.PNG
retrofit/images/Threshold_Plot.PNG
retrofit/templates/__init__.py
retrofit/templates/model_insights_regression.html
retrofit-0.3.3.dist-info/licenses/LICENSE
retrofit-0.3.3.dist-info/METADATA
retrofit-0.3.3.dist-info/WHEEL
retrofit-0.3.3.dist-info/top_level.txt
retrofit-0.3.3.dist-info/RECORD
