Metadata-Version: 2.4
Name: retrofit
Version: 0.3.3
Summary: High-Performance ML Training, Scoring & Evaluation (Polars + GPU-Ready)
Home-page: https://github.com/AdrianAntico/retrofit
Author: Adrian Antico, Sean Benner
Author-email: adrianantico@gmail.com
License: MIT
Classifier: Development Status :: 4 - Beta
Classifier: License :: OSI Approved :: MIT License
Classifier: Programming Language :: Python
Classifier: Programming Language :: Python :: 3
Classifier: Programming Language :: Python :: 3.10
Classifier: Programming Language :: Python :: 3.11
Classifier: Programming Language :: Python :: 3.12
Classifier: Programming Language :: Python :: 3.13
Classifier: Programming Language :: Python :: 3.14
Classifier: Operating System :: OS Independent
Classifier: Intended Audience :: Developers
Classifier: Intended Audience :: Science/Research
Classifier: Topic :: Scientific/Engineering :: Artificial Intelligence
Requires-Python: >=3.10
License-File: LICENSE
Requires-Dist: polars
Requires-Dist: pandas
Requires-Dist: numpy
Requires-Dist: scipy
Requires-Dist: catboost
Requires-Dist: xgboost
Requires-Dist: lightgbm
Requires-Dist: QuickEcharts
Requires-Dist: PolarsFE
Requires-Dist: pyarrow
Requires-Dist: scikit-learn
Requires-Dist: jinja2
Dynamic: license-file
